hashfish/__init__.py
hashfish-1.1.0.dist-info/LICENSE.txt
hashfish-1.1.0.dist-info/METADATA
hashfish-1.1.0.dist-info/WHEEL
hashfish-1.1.0.dist-info/top_level.txt
hashfish-1.1.0.dist-info/RECORD
