Metadata-Version: 2.1
Name: hashfish
Version: 1.1.0
Summary: Salty HMACs!
Author: Pigeon Nation
License: MIT
Classifier: Programming Language :: Python :: 3
Classifier: License :: OSI Approved :: MIT License
Classifier: Operating System :: OS Independent
Classifier: Topic :: Security :: Cryptography
License-File: LICENSE.txt
